rpi_artic_lib/GPIO/initGPIO.py
rpi_artic_lib/GPIO/inout.py
rpi_artic_lib/GPIO/input.py
rpi_artic_lib/GPIO/output.py
rpi_artic_lib/GPIO/port.py
rpi_artic_lib/screenLCD.py
rpi_artic_lib/status.py
rpi_artic_lib-0.1.2.dist-info/LICENSE
rpi_artic_lib-0.1.2.dist-info/METADATA
rpi_artic_lib-0.1.2.dist-info/WHEEL
rpi_artic_lib-0.1.2.dist-info/RECORD
